campfires/__init__.py
campfires/core/__init__.py
campfires/core/audio_processor.py
campfires/core/audio_utils.py
campfires/core/camper.py
campfires/core/campfire.py
campfires/core/context_path.py
campfires/core/default_auditor.py
campfires/core/enhanced_orchestration.py
campfires/core/factory.py
campfires/core/html_report_generator.py
campfires/core/manifest_loader.py
campfires/core/multimodal_camper_mixin.py
campfires/core/multimodal_ollama.py
campfires/core/multimodal_openrouter.py
campfires/core/multimodal_prompts.py
campfires/core/multimodal_torch.py
campfires/core/ollama.py
campfires/core/openrouter.py
campfires/core/orchestration.py
campfires/core/party_orchestrator.py
campfires/core/rag_state_manager.py
campfires/core/state_manager.py
campfires/core/topology_manager.py
campfires/core/torch.py
campfires/core/torch_rules.py
campfires/mcp/__init__.py
campfires/mcp/ollama_protocol.py
campfires/mcp/openrouter_protocol.py
campfires/mcp/protocol.py
campfires/mcp/transport.py
campfires/party_box/__init__.py
campfires/party_box/box_driver.py
campfires/party_box/local_driver.py
campfires/party_box/metadata_extractor.py
campfires/party_box/multimodal_local_driver.py
campfires/utils/__init__.py
campfires/utils/cleanup.py
campfires/utils/hash_utils.py
campfires/utils/template_loader.py
campfires/zeitgeist/__init__.py
campfires/zeitgeist/config.py
campfires/zeitgeist/opinion_analyzer.py
campfires/zeitgeist/role_query_generator.py
campfires/zeitgeist/zeitgeist_engine.py
campfires-0.4.1.dist-info/licenses/LICENSE
campfires-0.4.1.dist-info/METADATA
campfires-0.4.1.dist-info/WHEEL
campfires-0.4.1.dist-info/top_level.txt
campfires-0.4.1.dist-info/RECORD
